shellingham/__init__.py
shellingham/_core.py
shellingham/nt.py
shellingham/posix/__init__.py
shellingham/posix/_core.py
shellingham/posix/proc.py
shellingham/posix/ps.py
shellingham-1.5.1.dist-info/LICENSE
shellingham-1.5.1.dist-info/METADATA
shellingham-1.5.1.dist-info/WHEEL
shellingham-1.5.1.dist-info/top_level.txt
shellingham-1.5.1.dist-info/zip-safe
shellingham-1.5.1.dist-info/RECORD
