Metadata-Version: 2.1
Name: shellingham
Version: 1.5.1
Summary: Tool to Detect Surrounding Shell
Home-page: https://github.com/sarugaku/shellingham
Author: Tzu-ping Chung
Author-email: uranusjr@gmail.com
License: ISC License
Keywords: shell
Classifier: Development Status :: 3 - Alpha
Classifier: Environment :: Console
Classifier: Intended Audience :: Developers
Classifier: License :: OSI Approved :: ISC License (ISCL)
Classifier: Operating System :: OS Independent
Classifier: Programming Language :: Python :: 3 :: Only
Classifier: Programming Language :: Python :: 3.7
Classifier: Programming Language :: Python :: 3.8
Classifier: Programming Language :: Python :: 3.9
Classifier: Programming Language :: Python :: 3.10
Classifier: Topic :: Software Development :: Libraries :: Python Modules
Requires-Python: >=3.7
License-File: LICENSE
